pyddiscordwrapper/__init__.py
pyddiscordwrapper/_client.py
pyddiscordwrapper/_endpoints.py
pyddiscordwrapper/_urls.py
pyddiscordwrapper/types/AuthToken.py
pyddiscordwrapper/types/Channel.py
pyddiscordwrapper/types/Emoji.py
pyddiscordwrapper/types/Guild.py
pyddiscordwrapper/types/Member.py
pyddiscordwrapper/types/Role.py
pyddiscordwrapper/types/User.py
pyddiscordwrapper/types/__init__.py
pyddiscordwrapper-0.1.0.dist-info/LICENSE
pyddiscordwrapper-0.1.0.dist-info/WHEEL
pyddiscordwrapper-0.1.0.dist-info/METADATA
pyddiscordwrapper-0.1.0.dist-info/RECORD
